arglite/__init__.py
arglite/arglite.py
arglite/argument.py
arglite/code.py
arglite-0.9.7.dist-info/licenses/LICENSE
arglite-0.9.7.dist-info/METADATA
arglite-0.9.7.dist-info/WHEEL
arglite-0.9.7.dist-info/top_level.txt
arglite-0.9.7.dist-info/RECORD
