Metadata-Version: 2.4
Name: arglite
Version: 0.9.7
Summary: A lightweight, dynamic arg parser for fun, but not profit.
Home-page: https://github.com/dluman/arglite
License-File: LICENSE
Requires-Dist: rich
Dynamic: description
Dynamic: description-content-type
Dynamic: home-page
Dynamic: license-file
Dynamic: requires-dist
Dynamic: summary
